Assign10tnguyen4/__init__.py
Assign10tnguyen4/clean_tweet.py
Assign10tnguyen4/get_tweet_sentiment.py
Assign10tnguyen4/sentimentAdd.py
Assign10tnguyen4/sentimentFinder.py
Assign10tnguyen4/tweetRatio.py
Assign10tnguyen4-0.0.1.dist-info/METADATA
Assign10tnguyen4-0.0.1.dist-info/WHEEL
Assign10tnguyen4-0.0.1.dist-info/top_level.txt
Assign10tnguyen4-0.0.1.dist-info/RECORD
