Metadata-Version: 2.1
Name: Assign10tnguyen4
Version: 0.0.1
Summary: Sentiment Finder for tweets
Author: Tommy Nguyen
Author-email: <tnguyen4@g.emporia.edu>
Keywords: python,sentimentFinder
Classifier: Development Status :: 3 - Alpha
Classifier: Intended Audience :: Education
Classifier: Programming Language :: Python :: 2
Classifier: Programming Language :: Python :: 3
Classifier: Operating System :: MacOS :: MacOS X
Classifier: Operating System :: Microsoft :: Windows
